airunner/__init__.py
airunner/alembic.ini
airunner/app.py
airunner/app_installer.py
airunner/base_plugin.py
airunner/enums.py
airunner/feather_rc.py
airunner/installer.py
airunner/launcher.py
airunner/main.py
airunner/plugin_loader.py
airunner/settings.py
airunner/setup_database.py
airunner/alembic/env.py
airunner/alembic/script.py.mako
airunner/api/__init__.py
airunner/api/api.py
airunner/api/api_manager.py
airunner/api/api_service_base.py
airunner/api/art_services.py
airunner/api/canvas_services.py
airunner/api/chatbot_services.py
airunner/api/embedding_services.py
airunner/api/image_filter_services.py
airunner/api/llm_services.py
airunner/api/lora_services.py
airunner/api/nodegraph_services.py
airunner/api/stt_services.py
airunner/api/tool_services.py
airunner/api/tts_services.py
airunner/api/video_services.py
airunner/api/tool_services/__init__.py
airunner/api/tool_services/search.py
airunner/api/tool_services/tool_service.py
airunner/bin/__init__.py
airunner/bin/build_ui.py
airunner/bin/compile_translations.py
airunner/bin/coverage_report.py
airunner/bin/docker_build.py
airunner/bin/docker_wrapper.py
airunner/bin/generate_cert.py
airunner/bin/generate_migration.py
airunner/bin/process_qss.py
airunner/bin/run_tests.py
airunner/bin/setup_mathjax.py
airunner/components/__init__.py
airunner/components/browser/__init__.py
airunner/components/browser/data/__init__.py
airunner/components/browser/data/settings.py
airunner/components/browser/gui/__init__.py
airunner/components/browser/gui/enums.py
airunner/components/browser/gui/settings.py
airunner/components/browser/gui/widgets/__init__.py
airunner/components/browser/gui/widgets/browser_widget.py
airunner/components/browser/gui/widgets/items_model.py
airunner/components/browser/gui/widgets/items_widget.py
airunner/components/browser/gui/widgets/mixins/__init__.py
airunner/components/browser/gui/widgets/mixins/cache_mixin.py
airunner/components/browser/gui/widgets/mixins/navigation_mixin.py
airunner-4.11.3.dist-info/licenses/LICENSE
airunner-4.11.3.dist-info/METADATA
airunner-4.11.3.dist-info/WHEEL
airunner-4.11.3.dist-info/entry_points.txt
airunner-4.11.3.dist-info/top_level.txt
airunner-4.11.3.dist-info/RECORD
