Metadata-Version: 2.4
Name: airunner
Version: 4.11.3
Summary: Run local opensource AI models (Stable Diffusion, LLMs, TTS, STT, chatbots) in a lightweight Python GUI
Home-page: https://github.com/Capsize-Games/airunner
Author: Capsize LLC
Author-email: contact@capsizegames.com
License: Apache-2.0
Keywords: llm,pyside6,gui,local llm,stable diffusion,generative ai,local chatgpt,text-to-speech,speech-to-text,open source chatbot,python ai runner
Requires-Python: >=3.13.3
License-File: LICENSE
Requires-Dist: torch
Requires-Dist: torchvision
Requires-Dist: torchaudio
Requires-Dist: torchao
Requires-Dist: accelerate==1.7.0
Requires-Dist: huggingface-hub<1.0,>=0.24.0
Requires-Dist: tokenizers==0.21.1
Requires-Dist: optimum==1.25.1
Requires-Dist: numpy==2.2.5
Requires-Dist: pillow==10.4.0
Requires-Dist: alembic==1.15.2
Requires-Dist: aiosqlite==0.21.0
Requires-Dist: sqlalchemy==2.0.38
Requires-Dist: setuptools==78.1.1
Requires-Dist: etils[epath]==1.12.2
Requires-Dist: jinja2==3.1.6
Provides-Extra: nvidia
Requires-Dist: nvidia-cuda-runtime-cu12; extra == "nvidia"
Provides-Extra: huggingface
Requires-Dist: diffusers==0.33.1; extra == "huggingface"
Requires-Dist: controlnet_aux==0.0.10; extra == "huggingface"
Requires-Dist: safetensors==0.5.2; extra == "huggingface"
Requires-Dist: compel==2.1.0; extra == "huggingface"
Requires-Dist: transformers==4.51.3; extra == "huggingface"
Requires-Dist: datasets==3.6.0; extra == "huggingface"
Requires-Dist: peft==0.15.2; extra == "huggingface"
Provides-Extra: gui
Requires-Dist: PySide6==6.9.0; extra == "gui"
Requires-Dist: PySide6_Addons==6.9.0; extra == "gui"
Requires-Dist: PySide6_Essentials==6.9.0; extra == "gui"
Provides-Extra: linux
Requires-Dist: tensorrt==10.9.0.34; extra == "linux"
Provides-Extra: dev
Requires-Dist: pytest; extra == "dev"
Requires-Dist: python-dotenv==1.0.1; extra == "dev"
Requires-Dist: coverage==7.8.0; extra == "dev"
Requires-Dist: black==25.1.0; extra == "dev"
Requires-Dist: pyinstaller==6.12.0; extra == "dev"
Requires-Dist: flake8==7.2.0; extra == "dev"
Requires-Dist: mypy==1.16.0; extra == "dev"
Provides-Extra: art
Requires-Dist: DeepCache==0.1.1; extra == "art"
Requires-Dist: tomesd==0.1.3; extra == "art"
Provides-Extra: llm
Requires-Dist: bitsandbytes==0.45.5; extra == "llm"
Requires-Dist: sentence_transformers==3.4.1; extra == "llm"
Requires-Dist: sounddevice==0.5.1; extra == "llm"
Requires-Dist: pyttsx3==2.91; extra == "llm"
Requires-Dist: cryptography==44.0.3; extra == "llm"
Requires-Dist: sumy==0.11.0; extra == "llm"
Requires-Dist: sentencepiece==0.2.0; extra == "llm"
Requires-Dist: lingua-language-detector==2.1.0; extra == "llm"
Requires-Dist: markdown==3.8; extra == "llm"
Provides-Extra: agents
Requires-Dist: llama-index==0.12.36; extra == "agents"
Requires-Dist: llama-index-readers-file==0.4.7; extra == "agents"
Requires-Dist: llama-index-readers-web==0.4.1; extra == "agents"
Requires-Dist: llama-index-llms-huggingface==0.5.0; extra == "agents"
Requires-Dist: llama-index-llms-groq==0.3.1; extra == "agents"
Requires-Dist: llama-index-embeddings-mistralai==0.3.0; extra == "agents"
Requires-Dist: llama-index-vector-stores-faiss==0.4.0; extra == "agents"
Requires-Dist: llama-index-embeddings-huggingface==0.5.4; extra == "agents"
Requires-Dist: llama-index-llms-openrouter==0.3.1; extra == "agents"
Requires-Dist: langchain-community==0.3.24; extra == "agents"
Requires-Dist: EbookLib==0.19; extra == "agents"
Requires-Dist: html2text==2024.2.26; extra == "agents"
Requires-Dist: rake_nltk==1.0.6; extra == "agents"
Provides-Extra: ollama
Requires-Dist: llama-index-llms-ollama==0.5.4; extra == "ollama"
Provides-Extra: llm-weather
Requires-Dist: requests-cache==1.2.1; extra == "llm-weather"
Requires-Dist: retry-requests==2.0.0; extra == "llm-weather"
Requires-Dist: openmeteo_requests==1.4.0; extra == "llm-weather"
Provides-Extra: tts
Requires-Dist: inflect==7.5.0; extra == "tts"
Requires-Dist: pycountry==24.6.1; extra == "tts"
Requires-Dist: librosa==0.11.0; extra == "tts"
Provides-Extra: rabbitmq
Requires-Dist: pika; extra == "rabbitmq"
Provides-Extra: openvoice
Requires-Dist: librosa==0.11.0; extra == "openvoice"
Requires-Dist: pydub==0.25.1; extra == "openvoice"
Requires-Dist: wavmark==0.0.3; extra == "openvoice"
Requires-Dist: eng_to_ipa==0.0.2; extra == "openvoice"
Requires-Dist: inflect==7.5.0; extra == "openvoice"
Requires-Dist: unidecode==1.4.0; extra == "openvoice"
Requires-Dist: langid==1.1.6; extra == "openvoice"
Provides-Extra: melotts
Requires-Dist: txtsplit==1.0.0; extra == "melotts"
Requires-Dist: cached_path==1.7.3; extra == "melotts"
Requires-Dist: num2words==0.5.14; extra == "melotts"
Requires-Dist: g2p_en==2.1.0; extra == "melotts"
Requires-Dist: anyascii==0.3.2; extra == "melotts"
Requires-Dist: loguru==0.7.3; extra == "melotts"
Provides-Extra: openvoice-cn
Requires-Dist: pypinyin==0.54.0; extra == "openvoice-cn"
Requires-Dist: jieba==0.42.1; extra == "openvoice-cn"
Requires-Dist: cn2an==0.5.23; extra == "openvoice-cn"
Provides-Extra: openvoice-jp
Requires-Dist: unidic_lite==1.0.8; extra == "openvoice-jp"
Requires-Dist: unidic==1.1.0; extra == "openvoice-jp"
Requires-Dist: mecab-python3==1.0.10; extra == "openvoice-jp"
Requires-Dist: fugashi==1.4.0; extra == "openvoice-jp"
Requires-Dist: pykakasi==2.3.0; extra == "openvoice-jp"
Provides-Extra: openvoice-kr
Requires-Dist: jamo==0.4.1; extra == "openvoice-kr"
Requires-Dist: python-mecab-ko==1.3.7; extra == "openvoice-kr"
Requires-Dist: python-mecab-ko-dic==2.1.1.post2; extra == "openvoice-kr"
Provides-Extra: openvoice-tw
Requires-Dist: g2pkk>=0.1.2; extra == "openvoice-tw"
Provides-Extra: gruut-support
Requires-Dist: gruut[de,es,fr]==2.4.0; extra == "gruut-support"
Requires-Dist: networkx==3.4.2; extra == "gruut-support"
Provides-Extra: search
Requires-Dist: duckduckgo-search>=8.0.2; extra == "search"
Requires-Dist: aiohttp>=3.11.0; extra == "search"
Requires-Dist: google-api-python-client>=2.170.0; extra == "search"
Requires-Dist: wikipedia>=1.4.0; extra == "search"
Requires-Dist: scrapy==2.13.1; extra == "search"
Requires-Dist: trafilatura==2.0.0; extra == "search"
Provides-Extra: all
Requires-Dist: nvidia-cuda-runtime-cu12; extra == "all"
Requires-Dist: diffusers==0.33.1; extra == "all"
Requires-Dist: controlnet_aux==0.0.10; extra == "all"
Requires-Dist: safetensors==0.5.2; extra == "all"
Requires-Dist: compel==2.1.0; extra == "all"
Requires-Dist: transformers==4.51.3; extra == "all"
Requires-Dist: datasets==3.6.0; extra == "all"
Requires-Dist: peft==0.15.2; extra == "all"
Requires-Dist: PySide6==6.9.0; extra == "all"
Requires-Dist: PySide6_Addons==6.9.0; extra == "all"
Requires-Dist: PySide6_Essentials==6.9.0; extra == "all"
Requires-Dist: tensorrt==10.9.0.34; extra == "all"
Requires-Dist: DeepCache==0.1.1; extra == "all"
Requires-Dist: tomesd==0.1.3; extra == "all"
Requires-Dist: bitsandbytes==0.45.5; extra == "all"
Requires-Dist: sentence_transformers==3.4.1; extra == "all"
Requires-Dist: sounddevice==0.5.1; extra == "all"
Requires-Dist: pyttsx3==2.91; extra == "all"
Requires-Dist: cryptography==44.0.3; extra == "all"
Requires-Dist: sumy==0.11.0; extra == "all"
Requires-Dist: sentencepiece==0.2.0; extra == "all"
Requires-Dist: lingua-language-detector==2.1.0; extra == "all"
Requires-Dist: markdown==3.8; extra == "all"
Requires-Dist: llama-index==0.12.36; extra == "all"
Requires-Dist: llama-index-readers-file==0.4.7; extra == "all"
Requires-Dist: llama-index-readers-web==0.4.1; extra == "all"
Requires-Dist: llama-index-llms-huggingface==0.5.0; extra == "all"
Requires-Dist: llama-index-llms-groq==0.3.1; extra == "all"
Requires-Dist: llama-index-embeddings-mistralai==0.3.0; extra == "all"
Requires-Dist: llama-index-vector-stores-faiss==0.4.0; extra == "all"
Requires-Dist: llama-index-embeddings-huggingface==0.5.4; extra == "all"
Requires-Dist: llama-index-llms-openrouter==0.3.1; extra == "all"
Requires-Dist: langchain-community==0.3.24; extra == "all"
Requires-Dist: EbookLib==0.19; extra == "all"
Requires-Dist: html2text==2024.2.26; extra == "all"
Requires-Dist: rake_nltk==1.0.6; extra == "all"
Requires-Dist: llama-index-llms-ollama==0.5.4; extra == "all"
Requires-Dist: requests-cache==1.2.1; extra == "all"
Requires-Dist: retry-requests==2.0.0; extra == "all"
Requires-Dist: openmeteo_requests==1.4.0; extra == "all"
Requires-Dist: inflect==7.5.0; extra == "all"
Requires-Dist: pycountry==24.6.1; extra == "all"
Requires-Dist: librosa==0.11.0; extra == "all"
Requires-Dist: pika; extra == "all"
Requires-Dist: librosa==0.11.0; extra == "all"
Requires-Dist: pydub==0.25.1; extra == "all"
Requires-Dist: wavmark==0.0.3; extra == "all"
Requires-Dist: eng_to_ipa==0.0.2; extra == "all"
Requires-Dist: inflect==7.5.0; extra == "all"
Requires-Dist: unidecode==1.4.0; extra == "all"
Requires-Dist: langid==1.1.6; extra == "all"
Requires-Dist: txtsplit==1.0.0; extra == "all"
Requires-Dist: cached_path==1.7.3; extra == "all"
Requires-Dist: num2words==0.5.14; extra == "all"
Requires-Dist: g2p_en==2.1.0; extra == "all"
Requires-Dist: anyascii==0.3.2; extra == "all"
Requires-Dist: loguru==0.7.3; extra == "all"
Requires-Dist: pypinyin==0.54.0; extra == "all"
Requires-Dist: jieba==0.42.1; extra == "all"
Requires-Dist: cn2an==0.5.23; extra == "all"
Requires-Dist: unidic_lite==1.0.8; extra == "all"
Requires-Dist: unidic==1.1.0; extra == "all"
Requires-Dist: mecab-python3==1.0.10; extra == "all"
Requires-Dist: fugashi==1.4.0; extra == "all"
Requires-Dist: pykakasi==2.3.0; extra == "all"
Requires-Dist: jamo==0.4.1; extra == "all"
Requires-Dist: python-mecab-ko==1.3.7; extra == "all"
Requires-Dist: python-mecab-ko-dic==2.1.1.post2; extra == "all"
Requires-Dist: g2pkk>=0.1.2; extra == "all"
Requires-Dist: gruut[de,es,fr]==2.4.0; extra == "all"
Requires-Dist: networkx==3.4.2; extra == "all"
Requires-Dist: duckduckgo-search>=8.0.2; extra == "all"
Requires-Dist: aiohttp>=3.11.0; extra == "all"
Requires-Dist: google-api-python-client>=2.170.0; extra == "all"
Requires-Dist: wikipedia>=1.4.0; extra == "all"
Requires-Dist: scrapy==2.13.1; extra == "all"
Requires-Dist: trafilatura==2.0.0; extra == "all"
Requires-Dist: nvidia-cuda-runtime-cu12; extra == "all"
Requires-Dist: diffusers==0.33.1; extra == "all"
Requires-Dist: controlnet_aux==0.0.10; extra == "all"
Requires-Dist: safetensors==0.5.2; extra == "all"
Requires-Dist: compel==2.1.0; extra == "all"
Requires-Dist: transformers==4.51.3; extra == "all"
Requires-Dist: datasets==3.6.0; extra == "all"
Requires-Dist: peft==0.15.2; extra == "all"
Requires-Dist: PySide6==6.9.0; extra == "all"
Requires-Dist: PySide6_Addons==6.9.0; extra == "all"
Requires-Dist: PySide6_Essentials==6.9.0; extra == "all"
Requires-Dist: tensorrt==10.9.0.34; extra == "all"
Requires-Dist: pytest; extra == "all"
Requires-Dist: python-dotenv==1.0.1; extra == "all"
Requires-Dist: coverage==7.8.0; extra == "all"
Requires-Dist: black==25.1.0; extra == "all"
Requires-Dist: pyinstaller==6.12.0; extra == "all"
Requires-Dist: flake8==7.2.0; extra == "all"
Requires-Dist: mypy==1.16.0; extra == "all"
Requires-Dist: DeepCache==0.1.1; extra == "all"
Requires-Dist: tomesd==0.1.3; extra == "all"
Requires-Dist: bitsandbytes==0.45.5; extra == "all"
Requires-Dist: sentence_transformers==3.4.1; extra == "all"
Requires-Dist: sounddevice==0.5.1; extra == "all"
Requires-Dist: pyttsx3==2.91; extra == "all"
Requires-Dist: cryptography==44.0.3; extra == "all"
Requires-Dist: sumy==0.11.0; extra == "all"
Requires-Dist: sentencepiece==0.2.0; extra == "all"
Requires-Dist: lingua-language-detector==2.1.0; extra == "all"
Requires-Dist: markdown==3.8; extra == "all"
Requires-Dist: llama-index==0.12.36; extra == "all"
Requires-Dist: llama-index-readers-file==0.4.7; extra == "all"
Requires-Dist: llama-index-readers-web==0.4.1; extra == "all"
Requires-Dist: llama-index-llms-huggingface==0.5.0; extra == "all"
Requires-Dist: llama-index-llms-groq==0.3.1; extra == "all"
Requires-Dist: llama-index-embeddings-mistralai==0.3.0; extra == "all"
Requires-Dist: llama-index-vector-stores-faiss==0.4.0; extra == "all"
Requires-Dist: llama-index-embeddings-huggingface==0.5.4; extra == "all"
Requires-Dist: llama-index-llms-openrouter==0.3.1; extra == "all"
Requires-Dist: langchain-community==0.3.24; extra == "all"
Requires-Dist: EbookLib==0.19; extra == "all"
Requires-Dist: html2text==2024.2.26; extra == "all"
Requires-Dist: rake_nltk==1.0.6; extra == "all"
Requires-Dist: llama-index-llms-ollama==0.5.4; extra == "all"
Requires-Dist: requests-cache==1.2.1; extra == "all"
Requires-Dist: retry-requests==2.0.0; extra == "all"
Requires-Dist: openmeteo_requests==1.4.0; extra == "all"
Requires-Dist: inflect==7.5.0; extra == "all"
Requires-Dist: pycountry==24.6.1; extra == "all"
Requires-Dist: librosa==0.11.0; extra == "all"
Requires-Dist: pika; extra == "all"
Requires-Dist: librosa==0.11.0; extra == "all"
Requires-Dist: pydub==0.25.1; extra == "all"
Requires-Dist: wavmark==0.0.3; extra == "all"
Requires-Dist: eng_to_ipa==0.0.2; extra == "all"
Requires-Dist: inflect==7.5.0; extra == "all"
Requires-Dist: unidecode==1.4.0; extra == "all"
Requires-Dist: langid==1.1.6; extra == "all"
Requires-Dist: txtsplit==1.0.0; extra == "all"
Requires-Dist: cached_path==1.7.3; extra == "all"
Requires-Dist: num2words==0.5.14; extra == "all"
Requires-Dist: g2p_en==2.1.0; extra == "all"
Requires-Dist: anyascii==0.3.2; extra == "all"
Requires-Dist: loguru==0.7.3; extra == "all"
Requires-Dist: pypinyin==0.54.0; extra == "all"
Requires-Dist: jieba==0.42.1; extra == "all"
Requires-Dist: cn2an==0.5.23; extra == "all"
Requires-Dist: unidic_lite==1.0.8; extra == "all"
Requires-Dist: unidic==1.1.0; extra == "all"
Requires-Dist: mecab-python3==1.0.10; extra == "all"
Requires-Dist: fugashi==1.4.0; extra == "all"
Requires-Dist: pykakasi==2.3.0; extra == "all"
Requires-Dist: jamo==0.4.1; extra == "all"
Requires-Dist: python-mecab-ko==1.3.7; extra == "all"
Requires-Dist: python-mecab-ko-dic==2.1.1.post2; extra == "all"
Requires-Dist: g2pkk>=0.1.2; extra == "all"
Requires-Dist: gruut[de,es,fr]==2.4.0; extra == "all"
Requires-Dist: networkx==3.4.2; extra == "all"
Requires-Dist: duckduckgo-search>=8.0.2; extra == "all"
Requires-Dist: aiohttp>=3.11.0; extra == "all"
Requires-Dist: google-api-python-client>=2.170.0; extra == "all"
Requires-Dist: wikipedia>=1.4.0; extra == "all"
Requires-Dist: scrapy==2.13.1; extra == "all"
Requires-Dist: trafilatura==2.0.0; extra == "all"
Requires-Dist: nvidia-cuda-runtime-cu12; extra == "all"
Requires-Dist: diffusers==0.33.1; extra == "all"
Requires-Dist: controlnet_aux==0.0.10; extra == "all"
Requires-Dist: safetensors==0.5.2; extra == "all"
Requires-Dist: compel==2.1.0; extra == "all"
Requires-Dist: transformers==4.51.3; extra == "all"
Requires-Dist: datasets==3.6.0; extra == "all"
Requires-Dist: peft==0.15.2; extra == "all"
Requires-Dist: PySide6==6.9.0; extra == "all"
Requires-Dist: PySide6_Addons==6.9.0; extra == "all"
Requires-Dist: PySide6_Essentials==6.9.0; extra == "all"
Requires-Dist: tensorrt==10.9.0.34; extra == "all"
Requires-Dist: DeepCache==0.1.1; extra == "all"
Requires-Dist: tomesd==0.1.3; extra == "all"
Requires-Dist: bitsandbytes==0.45.5; extra == "all"
Requires-Dist: sentence_transformers==3.4.1; extra == "all"
Requires-Dist: sounddevice==0.5.1; extra == "all"
Requires-Dist: pyttsx3==2.91; extra == "all"
Requires-Dist: cryptography==44.0.3; extra == "all"
Requires-Dist: sumy==0.11.0; extra == "all"
Requires-Dist: sentencepiece==0.2.0; extra == "all"
Requires-Dist: lingua-language-detector==2.1.0; extra == "all"
Requires-Dist: markdown==3.8; extra == "all"
Requires-Dist: llama-index==0.12.36; extra == "all"
Requires-Dist: llama-index-readers-file==0.4.7; extra == "all"
Requires-Dist: llama-index-readers-web==0.4.1; extra == "all"
Requires-Dist: llama-index-llms-huggingface==0.5.0; extra == "all"
Requires-Dist: llama-index-llms-groq==0.3.1; extra == "all"
Requires-Dist: llama-index-embeddings-mistralai==0.3.0; extra == "all"
Requires-Dist: llama-index-vector-stores-faiss==0.4.0; extra == "all"
Requires-Dist: llama-index-embeddings-huggingface==0.5.4; extra == "all"
Requires-Dist: llama-index-llms-openrouter==0.3.1; extra == "all"
Requires-Dist: langchain-community==0.3.24; extra == "all"
Requires-Dist: EbookLib==0.19; extra == "all"
Requires-Dist: html2text==2024.2.26; extra == "all"
Requires-Dist: rake_nltk==1.0.6; extra == "all"
Requires-Dist: llama-index-llms-ollama==0.5.4; extra == "all"
Requires-Dist: requests-cache==1.2.1; extra == "all"
Requires-Dist: retry-requests==2.0.0; extra == "all"
Requires-Dist: openmeteo_requests==1.4.0; extra == "all"
Requires-Dist: inflect==7.5.0; extra == "all"
Requires-Dist: pycountry==24.6.1; extra == "all"
Requires-Dist: librosa==0.11.0; extra == "all"
Requires-Dist: pika; extra == "all"
Requires-Dist: librosa==0.11.0; extra == "all"
Requires-Dist: pydub==0.25.1; extra == "all"
Requires-Dist: wavmark==0.0.3; extra == "all"
Requires-Dist: eng_to_ipa==0.0.2; extra == "all"
Requires-Dist: inflect==7.5.0; extra == "all"
Requires-Dist: unidecode==1.4.0; extra == "all"
Requires-Dist: langid==1.1.6; extra == "all"
Requires-Dist: txtsplit==1.0.0; extra == "all"
Requires-Dist: cached_path==1.7.3; extra == "all"
Requires-Dist: num2words==0.5.14; extra == "all"
Requires-Dist: g2p_en==2.1.0; extra == "all"
Requires-Dist: anyascii==0.3.2; extra == "all"
Requires-Dist: loguru==0.7.3; extra == "all"
Requires-Dist: pypinyin==0.54.0; extra == "all"
Requires-Dist: jieba==0.42.1; extra == "all"
Requires-Dist: cn2an==0.5.23; extra == "all"
Requires-Dist: unidic_lite==1.0.8; extra == "all"
Requires-Dist: unidic==1.1.0; extra == "all"
Requires-Dist: mecab-python3==1.0.10; extra == "all"
Requires-Dist: fugashi==1.4.0; extra == "all"
Requires-Dist: pykakasi==2.3.0; extra == "all"
Requires-Dist: jamo==0.4.1; extra == "all"
Requires-Dist: python-mecab-ko==1.3.7; extra == "all"
Requires-Dist: python-mecab-ko-dic==2.1.1.post2; extra == "all"
Requires-Dist: g2pkk>=0.1.2; extra == "all"
Requires-Dist: gruut[de,es,fr]==2.4.0; extra == "all"
Requires-Dist: networkx==3.4.2; extra == "all"
Requires-Dist: duckduckgo-search>=8.0.2; extra == "all"
Requires-Dist: aiohttp>=3.11.0; extra == "all"
Requires-Dist: google-api-python-client>=2.170.0; extra == "all"
Requires-Dist: wikipedia>=1.4.0; extra == "all"
Requires-Dist: scrapy==2.13.1; extra == "all"
Requires-Dist: trafilatura==2.0.0; extra == "all"
Provides-Extra: all-dev
Requires-Dist: nvidia-cuda-runtime-cu12; extra == "all-dev"
Requires-Dist: diffusers==0.33.1; extra == "all-dev"
Requires-Dist: controlnet_aux==0.0.10; extra == "all-dev"
Requires-Dist: safetensors==0.5.2; extra == "all-dev"
Requires-Dist: compel==2.1.0; extra == "all-dev"
Requires-Dist: transformers==4.51.3; extra == "all-dev"
Requires-Dist: datasets==3.6.0; extra == "all-dev"
Requires-Dist: peft==0.15.2; extra == "all-dev"
Requires-Dist: PySide6==6.9.0; extra == "all-dev"
Requires-Dist: PySide6_Addons==6.9.0; extra == "all-dev"
Requires-Dist: PySide6_Essentials==6.9.0; extra == "all-dev"
Requires-Dist: tensorrt==10.9.0.34; extra == "all-dev"
Requires-Dist: pytest; extra == "all-dev"
Requires-Dist: python-dotenv==1.0.1; extra == "all-dev"
Requires-Dist: coverage==7.8.0; extra == "all-dev"
Requires-Dist: black==25.1.0; extra == "all-dev"
Requires-Dist: pyinstaller==6.12.0; extra == "all-dev"
Requires-Dist: flake8==7.2.0; extra == "all-dev"
Requires-Dist: mypy==1.16.0; extra == "all-dev"
Requires-Dist: DeepCache==0.1.1; extra == "all-dev"
Requires-Dist: tomesd==0.1.3; extra == "all-dev"
Requires-Dist: bitsandbytes==0.45.5; extra == "all-dev"
Requires-Dist: sentence_transformers==3.4.1; extra == "all-dev"
Requires-Dist: sounddevice==0.5.1; extra == "all-dev"
Requires-Dist: pyttsx3==2.91; extra == "all-dev"
Requires-Dist: cryptography==44.0.3; extra == "all-dev"
Requires-Dist: sumy==0.11.0; extra == "all-dev"
Requires-Dist: sentencepiece==0.2.0; extra == "all-dev"
Requires-Dist: lingua-language-detector==2.1.0; extra == "all-dev"
Requires-Dist: markdown==3.8; extra == "all-dev"
Requires-Dist: llama-index==0.12.36; extra == "all-dev"
Requires-Dist: llama-index-readers-file==0.4.7; extra == "all-dev"
Requires-Dist: llama-index-readers-web==0.4.1; extra == "all-dev"
Requires-Dist: llama-index-llms-huggingface==0.5.0; extra == "all-dev"
Requires-Dist: llama-index-llms-groq==0.3.1; extra == "all-dev"
Requires-Dist: llama-index-embeddings-mistralai==0.3.0; extra == "all-dev"
Requires-Dist: llama-index-vector-stores-faiss==0.4.0; extra == "all-dev"
Requires-Dist: llama-index-embeddings-huggingface==0.5.4; extra == "all-dev"
Requires-Dist: llama-index-llms-openrouter==0.3.1; extra == "all-dev"
Requires-Dist: langchain-community==0.3.24; extra == "all-dev"
Requires-Dist: EbookLib==0.19; extra == "all-dev"
Requires-Dist: html2text==2024.2.26; extra == "all-dev"
Requires-Dist: rake_nltk==1.0.6; extra == "all-dev"
Requires-Dist: llama-index-llms-ollama==0.5.4; extra == "all-dev"
Requires-Dist: requests-cache==1.2.1; extra == "all-dev"
Requires-Dist: retry-requests==2.0.0; extra == "all-dev"
Requires-Dist: openmeteo_requests==1.4.0; extra == "all-dev"
Requires-Dist: inflect==7.5.0; extra == "all-dev"
Requires-Dist: pycountry==24.6.1; extra == "all-dev"
Requires-Dist: librosa==0.11.0; extra == "all-dev"
Requires-Dist: pika; extra == "all-dev"
Requires-Dist: librosa==0.11.0; extra == "all-dev"
Requires-Dist: pydub==0.25.1; extra == "all-dev"
Requires-Dist: wavmark==0.0.3; extra == "all-dev"
Requires-Dist: eng_to_ipa==0.0.2; extra == "all-dev"
Requires-Dist: inflect==7.5.0; extra == "all-dev"
Requires-Dist: unidecode==1.4.0; extra == "all-dev"
Requires-Dist: langid==1.1.6; extra == "all-dev"
Requires-Dist: txtsplit==1.0.0; extra == "all-dev"
Requires-Dist: cached_path==1.7.3; extra == "all-dev"
Requires-Dist: num2words==0.5.14; extra == "all-dev"
Requires-Dist: g2p_en==2.1.0; extra == "all-dev"
Requires-Dist: anyascii==0.3.2; extra == "all-dev"
Requires-Dist: loguru==0.7.3; extra == "all-dev"
Requires-Dist: pypinyin==0.54.0; extra == "all-dev"
Requires-Dist: jieba==0.42.1; extra == "all-dev"
Requires-Dist: cn2an==0.5.23; extra == "all-dev"
Requires-Dist: unidic_lite==1.0.8; extra == "all-dev"
Requires-Dist: unidic==1.1.0; extra == "all-dev"
Requires-Dist: mecab-python3==1.0.10; extra == "all-dev"
Requires-Dist: fugashi==1.4.0; extra == "all-dev"
Requires-Dist: pykakasi==2.3.0; extra == "all-dev"
Requires-Dist: jamo==0.4.1; extra == "all-dev"
Requires-Dist: python-mecab-ko==1.3.7; extra == "all-dev"
Requires-Dist: python-mecab-ko-dic==2.1.1.post2; extra == "all-dev"
Requires-Dist: g2pkk>=0.1.2; extra == "all-dev"
Requires-Dist: gruut[de,es,fr]==2.4.0; extra == "all-dev"
Requires-Dist: networkx==3.4.2; extra == "all-dev"
Requires-Dist: duckduckgo-search>=8.0.2; extra == "all-dev"
Requires-Dist: aiohttp>=3.11.0; extra == "all-dev"
Requires-Dist: google-api-python-client>=2.170.0; extra == "all-dev"
Requires-Dist: wikipedia>=1.4.0; extra == "all-dev"
Requires-Dist: scrapy==2.13.1; extra == "all-dev"
Requires-Dist: trafilatura==2.0.0; extra == "all-dev"
Requires-Dist: nvidia-cuda-runtime-cu12; extra == "all-dev"
Requires-Dist: diffusers==0.33.1; extra == "all-dev"
Requires-Dist: controlnet_aux==0.0.10; extra == "all-dev"
Requires-Dist: safetensors==0.5.2; extra == "all-dev"
Requires-Dist: compel==2.1.0; extra == "all-dev"
Requires-Dist: transformers==4.51.3; extra == "all-dev"
Requires-Dist: datasets==3.6.0; extra == "all-dev"
Requires-Dist: peft==0.15.2; extra == "all-dev"
Requires-Dist: PySide6==6.9.0; extra == "all-dev"
Requires-Dist: PySide6_Addons==6.9.0; extra == "all-dev"
Requires-Dist: PySide6_Essentials==6.9.0; extra == "all-dev"
Requires-Dist: tensorrt==10.9.0.34; extra == "all-dev"
Requires-Dist: pytest; extra == "all-dev"
Requires-Dist: python-dotenv==1.0.1; extra == "all-dev"
Requires-Dist: coverage==7.8.0; extra == "all-dev"
Requires-Dist: black==25.1.0; extra == "all-dev"
Requires-Dist: pyinstaller==6.12.0; extra == "all-dev"
Requires-Dist: flake8==7.2.0; extra == "all-dev"
Requires-Dist: mypy==1.16.0; extra == "all-dev"
Requires-Dist: DeepCache==0.1.1; extra == "all-dev"
Requires-Dist: tomesd==0.1.3; extra == "all-dev"
Requires-Dist: bitsandbytes==0.45.5; extra == "all-dev"
Requires-Dist: sentence_transformers==3.4.1; extra == "all-dev"
Requires-Dist: sounddevice==0.5.1; extra == "all-dev"
Requires-Dist: pyttsx3==2.91; extra == "all-dev"
Requires-Dist: cryptography==44.0.3; extra == "all-dev"
Requires-Dist: sumy==0.11.0; extra == "all-dev"
Requires-Dist: sentencepiece==0.2.0; extra == "all-dev"
Requires-Dist: lingua-language-detector==2.1.0; extra == "all-dev"
Requires-Dist: markdown==3.8; extra == "all-dev"
Requires-Dist: llama-index==0.12.36; extra == "all-dev"
Requires-Dist: llama-index-readers-file==0.4.7; extra == "all-dev"
Requires-Dist: llama-index-readers-web==0.4.1; extra == "all-dev"
Requires-Dist: llama-index-llms-huggingface==0.5.0; extra == "all-dev"
Requires-Dist: llama-index-llms-groq==0.3.1; extra == "all-dev"
Requires-Dist: llama-index-embeddings-mistralai==0.3.0; extra == "all-dev"
Requires-Dist: llama-index-vector-stores-faiss==0.4.0; extra == "all-dev"
Requires-Dist: llama-index-embeddings-huggingface==0.5.4; extra == "all-dev"
Requires-Dist: llama-index-llms-openrouter==0.3.1; extra == "all-dev"
Requires-Dist: langchain-community==0.3.24; extra == "all-dev"
Requires-Dist: EbookLib==0.19; extra == "all-dev"
Requires-Dist: html2text==2024.2.26; extra == "all-dev"
Requires-Dist: rake_nltk==1.0.6; extra == "all-dev"
Requires-Dist: llama-index-llms-ollama==0.5.4; extra == "all-dev"
Requires-Dist: requests-cache==1.2.1; extra == "all-dev"
Requires-Dist: retry-requests==2.0.0; extra == "all-dev"
Requires-Dist: openmeteo_requests==1.4.0; extra == "all-dev"
Requires-Dist: inflect==7.5.0; extra == "all-dev"
Requires-Dist: pycountry==24.6.1; extra == "all-dev"
Requires-Dist: librosa==0.11.0; extra == "all-dev"
Requires-Dist: pika; extra == "all-dev"
Requires-Dist: librosa==0.11.0; extra == "all-dev"
Requires-Dist: pydub==0.25.1; extra == "all-dev"
Requires-Dist: wavmark==0.0.3; extra == "all-dev"
Requires-Dist: eng_to_ipa==0.0.2; extra == "all-dev"
Requires-Dist: inflect==7.5.0; extra == "all-dev"
Requires-Dist: unidecode==1.4.0; extra == "all-dev"
Requires-Dist: langid==1.1.6; extra == "all-dev"
Requires-Dist: txtsplit==1.0.0; extra == "all-dev"
Requires-Dist: cached_path==1.7.3; extra == "all-dev"
Requires-Dist: num2words==0.5.14; extra == "all-dev"
Requires-Dist: g2p_en==2.1.0; extra == "all-dev"
Requires-Dist: anyascii==0.3.2; extra == "all-dev"
Requires-Dist: loguru==0.7.3; extra == "all-dev"
Requires-Dist: pypinyin==0.54.0; extra == "all-dev"
Requires-Dist: jieba==0.42.1; extra == "all-dev"
Requires-Dist: cn2an==0.5.23; extra == "all-dev"
Requires-Dist: unidic_lite==1.0.8; extra == "all-dev"
Requires-Dist: unidic==1.1.0; extra == "all-dev"
Requires-Dist: mecab-python3==1.0.10; extra == "all-dev"
Requires-Dist: fugashi==1.4.0; extra == "all-dev"
Requires-Dist: pykakasi==2.3.0; extra == "all-dev"
Requires-Dist: jamo==0.4.1; extra == "all-dev"
Requires-Dist: python-mecab-ko==1.3.7; extra == "all-dev"
Requires-Dist: python-mecab-ko-dic==2.1.1.post2; extra == "all-dev"
Requires-Dist: g2pkk>=0.1.2; extra == "all-dev"
Requires-Dist: gruut[de,es,fr]==2.4.0; extra == "all-dev"
Requires-Dist: networkx==3.4.2; extra == "all-dev"
Requires-Dist: duckduckgo-search>=8.0.2; extra == "all-dev"
Requires-Dist: aiohttp>=3.11.0; extra == "all-dev"
Requires-Dist: google-api-python-client>=2.170.0; extra == "all-dev"
Requires-Dist: wikipedia>=1.4.0; extra == "all-dev"
Requires-Dist: scrapy==2.13.1; extra == "all-dev"
Requires-Dist: trafilatura==2.0.0; extra == "all-dev"
Requires-Dist: nvidia-cuda-runtime-cu12; extra == "all-dev"
Requires-Dist: diffusers==0.33.1; extra == "all-dev"
Requires-Dist: controlnet_aux==0.0.10; extra == "all-dev"
Requires-Dist: safetensors==0.5.2; extra == "all-dev"
Requires-Dist: compel==2.1.0; extra == "all-dev"
Requires-Dist: transformers==4.51.3; extra == "all-dev"
Requires-Dist: datasets==3.6.0; extra == "all-dev"
Requires-Dist: peft==0.15.2; extra == "all-dev"
Requires-Dist: PySide6==6.9.0; extra == "all-dev"
Requires-Dist: PySide6_Addons==6.9.0; extra == "all-dev"
Requires-Dist: PySide6_Essentials==6.9.0; extra == "all-dev"
Requires-Dist: tensorrt==10.9.0.34; extra == "all-dev"
Requires-Dist: pytest; extra == "all-dev"
Requires-Dist: python-dotenv==1.0.1; extra == "all-dev"
Requires-Dist: coverage==7.8.0; extra == "all-dev"
Requires-Dist: black==25.1.0; extra == "all-dev"
Requires-Dist: pyinstaller==6.12.0; extra == "all-dev"
Requires-Dist: flake8==7.2.0; extra == "all-dev"
Requires-Dist: mypy==1.16.0; extra == "all-dev"
Requires-Dist: DeepCache==0.1.1; extra == "all-dev"
Requires-Dist: tomesd==0.1.3; extra == "all-dev"
Requires-Dist: bitsandbytes==0.45.5; extra == "all-dev"
Requires-Dist: sentence_transformers==3.4.1; extra == "all-dev"
Requires-Dist: sounddevice==0.5.1; extra == "all-dev"
Requires-Dist: pyttsx3==2.91; extra == "all-dev"
Requires-Dist: cryptography==44.0.3; extra == "all-dev"
Requires-Dist: sumy==0.11.0; extra == "all-dev"
Requires-Dist: sentencepiece==0.2.0; extra == "all-dev"
Requires-Dist: lingua-language-detector==2.1.0; extra == "all-dev"
Requires-Dist: markdown==3.8; extra == "all-dev"
Requires-Dist: llama-index==0.12.36; extra == "all-dev"
Requires-Dist: llama-index-readers-file==0.4.7; extra == "all-dev"
Requires-Dist: llama-index-readers-web==0.4.1; extra == "all-dev"
Requires-Dist: llama-index-llms-huggingface==0.5.0; extra == "all-dev"
Requires-Dist: llama-index-llms-groq==0.3.1; extra == "all-dev"
Requires-Dist: llama-index-embeddings-mistralai==0.3.0; extra == "all-dev"
Requires-Dist: llama-index-vector-stores-faiss==0.4.0; extra == "all-dev"
Requires-Dist: llama-index-embeddings-huggingface==0.5.4; extra == "all-dev"
Requires-Dist: llama-index-llms-openrouter==0.3.1; extra == "all-dev"
Requires-Dist: langchain-community==0.3.24; extra == "all-dev"
Requires-Dist: EbookLib==0.19; extra == "all-dev"
Requires-Dist: html2text==2024.2.26; extra == "all-dev"
Requires-Dist: rake_nltk==1.0.6; extra == "all-dev"
Requires-Dist: llama-index-llms-ollama==0.5.4; extra == "all-dev"
Requires-Dist: requests-cache==1.2.1; extra == "all-dev"
Requires-Dist: retry-requests==2.0.0; extra == "all-dev"
Requires-Dist: openmeteo_requests==1.4.0; extra == "all-dev"
Requires-Dist: inflect==7.5.0; extra == "all-dev"
Requires-Dist: pycountry==24.6.1; extra == "all-dev"
Requires-Dist: librosa==0.11.0; extra == "all-dev"
Requires-Dist: pika; extra == "all-dev"
Requires-Dist: librosa==0.11.0; extra == "all-dev"
Requires-Dist: pydub==0.25.1; extra == "all-dev"
Requires-Dist: wavmark==0.0.3; extra == "all-dev"
Requires-Dist: eng_to_ipa==0.0.2; extra == "all-dev"
Requires-Dist: inflect==7.5.0; extra == "all-dev"
Requires-Dist: unidecode==1.4.0; extra == "all-dev"
Requires-Dist: langid==1.1.6; extra == "all-dev"
Requires-Dist: txtsplit==1.0.0; extra == "all-dev"
Requires-Dist: cached_path==1.7.3; extra == "all-dev"
Requires-Dist: num2words==0.5.14; extra == "all-dev"
Requires-Dist: g2p_en==2.1.0; extra == "all-dev"
Requires-Dist: anyascii==0.3.2; extra == "all-dev"
Requires-Dist: loguru==0.7.3; extra == "all-dev"
Requires-Dist: pypinyin==0.54.0; extra == "all-dev"
Requires-Dist: jieba==0.42.1; extra == "all-dev"
Requires-Dist: cn2an==0.5.23; extra == "all-dev"
Requires-Dist: unidic_lite==1.0.8; extra == "all-dev"
Requires-Dist: unidic==1.1.0; extra == "all-dev"
Requires-Dist: mecab-python3==1.0.10; extra == "all-dev"
Requires-Dist: fugashi==1.4.0; extra == "all-dev"
Requires-Dist: pykakasi==2.3.0; extra == "all-dev"
Requires-Dist: jamo==0.4.1; extra == "all-dev"
Requires-Dist: python-mecab-ko==1.3.7; extra == "all-dev"
Requires-Dist: python-mecab-ko-dic==2.1.1.post2; extra == "all-dev"
Requires-Dist: g2pkk>=0.1.2; extra == "all-dev"
Requires-Dist: gruut[de,es,fr]==2.4.0; extra == "all-dev"
Requires-Dist: networkx==3.4.2; extra == "all-dev"
Requires-Dist: duckduckgo-search>=8.0.2; extra == "all-dev"
Requires-Dist: aiohttp>=3.11.0; extra == "all-dev"
Requires-Dist: google-api-python-client>=2.170.0; extra == "all-dev"
Requires-Dist: wikipedia>=1.4.0; extra == "all-dev"
Requires-Dist: scrapy==2.13.1; extra == "all-dev"
Requires-Dist: trafilatura==2.0.0; extra == "all-dev"
Provides-Extra: windows
Requires-Dist: nvidia-cuda-runtime-cu12; extra == "windows"
Requires-Dist: diffusers==0.33.1; extra == "windows"
Requires-Dist: controlnet_aux==0.0.10; extra == "windows"
Requires-Dist: safetensors==0.5.2; extra == "windows"
Requires-Dist: compel==2.1.0; extra == "windows"
Requires-Dist: transformers==4.51.3; extra == "windows"
Requires-Dist: datasets==3.6.0; extra == "windows"
Requires-Dist: peft==0.15.2; extra == "windows"
Requires-Dist: PySide6==6.9.0; extra == "windows"
Requires-Dist: PySide6_Addons==6.9.0; extra == "windows"
Requires-Dist: PySide6_Essentials==6.9.0; extra == "windows"
Requires-Dist: pytest; extra == "windows"
Requires-Dist: python-dotenv==1.0.1; extra == "windows"
Requires-Dist: coverage==7.8.0; extra == "windows"
Requires-Dist: black==25.1.0; extra == "windows"
Requires-Dist: pyinstaller==6.12.0; extra == "windows"
Requires-Dist: flake8==7.2.0; extra == "windows"
Requires-Dist: mypy==1.16.0; extra == "windows"
Requires-Dist: DeepCache==0.1.1; extra == "windows"
Requires-Dist: tomesd==0.1.3; extra == "windows"
Requires-Dist: bitsandbytes==0.45.5; extra == "windows"
Requires-Dist: sentence_transformers==3.4.1; extra == "windows"
Requires-Dist: sounddevice==0.5.1; extra == "windows"
Requires-Dist: pyttsx3==2.91; extra == "windows"
Requires-Dist: cryptography==44.0.3; extra == "windows"
Requires-Dist: sumy==0.11.0; extra == "windows"
Requires-Dist: sentencepiece==0.2.0; extra == "windows"
Requires-Dist: lingua-language-detector==2.1.0; extra == "windows"
Requires-Dist: markdown==3.8; extra == "windows"
Requires-Dist: llama-index==0.12.36; extra == "windows"
Requires-Dist: llama-index-readers-file==0.4.7; extra == "windows"
Requires-Dist: llama-index-readers-web==0.4.1; extra == "windows"
Requires-Dist: llama-index-llms-huggingface==0.5.0; extra == "windows"
Requires-Dist: llama-index-llms-groq==0.3.1; extra == "windows"
Requires-Dist: llama-index-embeddings-mistralai==0.3.0; extra == "windows"
Requires-Dist: llama-index-vector-stores-faiss==0.4.0; extra == "windows"
Requires-Dist: llama-index-embeddings-huggingface==0.5.4; extra == "windows"
Requires-Dist: llama-index-llms-openrouter==0.3.1; extra == "windows"
Requires-Dist: langchain-community==0.3.24; extra == "windows"
Requires-Dist: EbookLib==0.19; extra == "windows"
Requires-Dist: html2text==2024.2.26; extra == "windows"
Requires-Dist: rake_nltk==1.0.6; extra == "windows"
Requires-Dist: llama-index-llms-ollama==0.5.4; extra == "windows"
Requires-Dist: requests-cache==1.2.1; extra == "windows"
Requires-Dist: retry-requests==2.0.0; extra == "windows"
Requires-Dist: openmeteo_requests==1.4.0; extra == "windows"
Requires-Dist: inflect==7.5.0; extra == "windows"
Requires-Dist: pycountry==24.6.1; extra == "windows"
Requires-Dist: librosa==0.11.0; extra == "windows"
Requires-Dist: pika; extra == "windows"
Requires-Dist: librosa==0.11.0; extra == "windows"
Requires-Dist: pydub==0.25.1; extra == "windows"
Requires-Dist: wavmark==0.0.3; extra == "windows"
Requires-Dist: eng_to_ipa==0.0.2; extra == "windows"
Requires-Dist: inflect==7.5.0; extra == "windows"
Requires-Dist: unidecode==1.4.0; extra == "windows"
Requires-Dist: langid==1.1.6; extra == "windows"
Requires-Dist: txtsplit==1.0.0; extra == "windows"
Requires-Dist: cached_path==1.7.3; extra == "windows"
Requires-Dist: num2words==0.5.14; extra == "windows"
Requires-Dist: g2p_en==2.1.0; extra == "windows"
Requires-Dist: anyascii==0.3.2; extra == "windows"
Requires-Dist: loguru==0.7.3; extra == "windows"
Requires-Dist: pypinyin==0.54.0; extra == "windows"
Requires-Dist: jieba==0.42.1; extra == "windows"
Requires-Dist: cn2an==0.5.23; extra == "windows"
Requires-Dist: unidic_lite==1.0.8; extra == "windows"
Requires-Dist: unidic==1.1.0; extra == "windows"
Requires-Dist: mecab-python3==1.0.10; extra == "windows"
Requires-Dist: fugashi==1.4.0; extra == "windows"
Requires-Dist: pykakasi==2.3.0; extra == "windows"
Requires-Dist: jamo==0.4.1; extra == "windows"
Requires-Dist: python-mecab-ko==1.3.7; extra == "windows"
Requires-Dist: python-mecab-ko-dic==2.1.1.post2; extra == "windows"
Requires-Dist: g2pkk>=0.1.2; extra == "windows"
Requires-Dist: gruut[de,es,fr]==2.4.0; extra == "windows"
Requires-Dist: networkx==3.4.2; extra == "windows"
Requires-Dist: duckduckgo-search>=8.0.2; extra == "windows"
Requires-Dist: aiohttp>=3.11.0; extra == "windows"
Requires-Dist: google-api-python-client>=2.170.0; extra == "windows"
Requires-Dist: wikipedia>=1.4.0; extra == "windows"
Requires-Dist: scrapy==2.13.1; extra == "windows"
Requires-Dist: trafilatura==2.0.0; extra == "windows"
Dynamic: author
Dynamic: author-email
Dynamic: description
Dynamic: description-content-type
Dynamic: home-page
Dynamic: keywords
Dynamic: license
Dynamic: license-file
Dynamic: provides-extra
Dynamic: requires-dist
Dynamic: requires-python
Dynamic: summary
